{
  "annotations": {
    "list": []
  },
  "editable": true,
  "graphTooltip": 0,
  "panels": [
    {
      "datasource": {
        "type": "prometheus",
        "uid": "Prometheus"
      },
      "fieldConfig": {
        "defaults": {
          "color": {
            "mode": "palette-classic"
          }
        },
        "overrides": []
      },
      "gridPos": {
        "h": 8,
        "w": 12,
        "x": 0,
        "y": 0
      },
      "id": 1,
      "targets": [
        {
          "expr": "up{job=\"dxcon-api\"}",
          "legendFormat": "API",
          "refId": "A"
        }
      ],
      "title": "DxCon API Up",
      "type": "timeseries"
    },
    {
      "datasource": {
        "type": "prometheus",
        "uid": "Prometheus"
      },
      "gridPos": {
        "h": 8,
        "w": 12,
        "x": 12,
        "y": 0
      },
      "id": 2,
      "targets": [
        {
          "expr": "up{job=\"postgres\"}",
          "legendFormat": "PostgreSQL",
          "refId": "A"
        }
      ],
      "title": "PostgreSQL Up",
      "type": "timeseries"
    }
  ],
  "schemaVersion": 39,
  "tags": ["dxcon", "staging"],
  "time": {
    "from": "now-6h",
    "to": "now"
  },
  "title": "DxCon Staging Overview",
  "uid": "dxcon-staging-overview",
  "version": 1
}
